interfaceagent/__init__.py
interfaceagent/cli.py
interfaceagent/datamodel.py
interfaceagent/utils.py
interfaceagent/version.py
interfaceagent/interface/__init__.py
interfaceagent/interface/browsermanager.py
interfaceagent/interface/model.py
interfaceagent/interface/planner.py
interfaceagent/interface/webbrowser.py
interfaceagent/web/__init__.py
interfaceagent/web/app.py
interfaceagent-0.0.1.dist-info/METADATA
interfaceagent-0.0.1.dist-info/WHEEL
interfaceagent-0.0.1.dist-info/entry_points.txt
interfaceagent-0.0.1.dist-info/top_level.txt
interfaceagent-0.0.1.dist-info/RECORD
