Metadata-Version: 2.1
Name: interfaceagent
Version: 0.0.1
Summary: Interface Agent: Addressing Tasks by Controlling Interfaces
Author-email: Victor Dibia <victor.dibia@gmail.com>
Project-URL: Homepage, https://github.com/yourusername/interfaceagent
Project-URL: Bug Tracker, https://github.com/yourusername/interfaceagent/issues
Classifier: Programming Language :: Python :: 3
Classifier: License :: OSI Approved :: MIT License
Classifier: Operating System :: OS Independent
Requires-Python: >=3.10
Requires-Dist: pydantic
Requires-Dist: loguru
Requires-Dist: uvicorn
Requires-Dist: typer
Requires-Dist: fastapi
Requires-Dist: python-multipart
Requires-Dist: playwright
Requires-Dist: openai
Provides-Extra: web
Requires-Dist: fastapi ; extra == 'web'
Requires-Dist: uvicorn ; extra == 'web'
